collective.richdescription-3.0.2-py3.11-nspkg.pth
collective/richdescription/__init__.py
collective/richdescription/behaviors.py
collective/richdescription/configure.zcml
collective/richdescription/description.pt
collective/richdescription/indexer.py
collective/richdescription/utils.py
collective/richdescription/profiles/default/catalog.xml
collective/richdescription/profiles/default/metadata.xml
collective.richdescription-3.0.2.dist-info/LICENCE.rst
collective.richdescription-3.0.2.dist-info/METADATA
collective.richdescription-3.0.2.dist-info/WHEEL
collective.richdescription-3.0.2.dist-info/entry_points.txt
collective.richdescription-3.0.2.dist-info/namespace_packages.txt
collective.richdescription-3.0.2.dist-info/top_level.txt
collective.richdescription-3.0.2.dist-info/RECORD
