Metadata-Version: 2.1
Name: collective.richdescription
Version: 3.0.2
Summary: Turns the Plone 'Description' field into Richtext/HTML
Home-page: https://github.com/collective/collective.richdescription
Author: Johannes Raggam
Author-email: raggam-nl@adm.at
License: GPLv2
Keywords: plone richtext dublincore
Classifier: Development Status :: 5 - Production/Stable
Classifier: Framework :: Plone
Classifier: Framework :: Plone :: 6.0
Classifier: Framework :: Plone :: Addon
Classifier: Framework :: Zope :: 5
Classifier: License :: OSI Approved :: GNU General Public License v2 (GPLv2)
Classifier: Operating System :: OS Independent
Classifier: Programming Language :: Python
Classifier: Programming Language :: Python :: 3.9
Classifier: Programming Language :: Python :: 3.10
Classifier: Programming Language :: Python :: 3.11
Requires-Python: >=3.9
License-File: LICENCE.rst
Requires-Dist: setuptools
Requires-Dist: plone.app.dexterity
Requires-Dist: plone.app.textfield
Requires-Dist: plone.app.z3cform
Requires-Dist: plone.autoform
Requires-Dist: plone.behavior
Requires-Dist: plone.dexterity
Requires-Dist: plone.indexer
Requires-Dist: plone.supermodel
Requires-Dist: Products.GenericSetup
Requires-Dist: zope.component
Requires-Dist: zope.i18nmessageid
Requires-Dist: zope.interface
Requires-Dist: zope.schema
